quran_detector/__init__.py
quran_detector/data_loader.py
quran_detector/dfiles/__init__.py
quran_detector/dfiles/nonTerminals.txt
quran_detector/dfiles/quran-index.xml
quran_detector/dfiles/quran-simple.txt
quran_detector/main.py
quran_detector/main_api.py
quran_detector/matcher.py
quran_detector/models.py
quran_detector/schemas.py
quran_detector/static/style.css
quran_detector/templates/index.html
quran_detector/utils.py
quran_detector-0.1.3.dist-info/METADATA
quran_detector-0.1.3.dist-info/WHEEL
quran_detector-0.1.3.dist-info/RECORD
